bobcat_miner/__init__.py
bobcat_miner/api.py
bobcat_miner/autopilot.py
bobcat_miner/base.py
bobcat_miner/bobcat.py
bobcat_miner/cli.py
bobcat_miner/connection.py
bobcat_miner/constants.py
bobcat_miner/diagnoser.py
bobcat_miner/errors.py
bobcat_miner/logger.py
bobcat_miner-0.16.6.dist-info/entry_points.txt
bobcat_miner-0.16.6.dist-info/LICENSE
bobcat_miner-0.16.6.dist-info/WHEEL
bobcat_miner-0.16.6.dist-info/METADATA
bobcat_miner-0.16.6.dist-info/RECORD
