Metadata-Version: 2.1
Name: bobcat-miner
Version: 0.16.6
Summary: Automate the Bobcat miner from the command line.
Home-page: https://github.com/aidanmelen/bobcat-miner-python
License: MIT
Keywords: helium,bobcat,miner
Author: Aidan Melen
Author-email: aidanmelen@protonmail.com
Requires-Python: >=3.8,<4.0
Classifier: License :: OSI Approved :: MIT License
Classifier: Programming Language :: Python :: 3
Classifier: Programming Language :: Python :: 3.10
Classifier: Programming Language :: Python :: 3.8
Classifier: Programming Language :: Python :: 3.9
Requires-Dist: aiohttp (>=3.8.1,<4.0.0)
Requires-Dist: backoff (>=1.11.1,<2.0.0)
Requires-Dist: beautifulsoup4 (>=4.10.0,<5.0.0)
Requires-Dist: click (>=8.0.3,<9.0.0)
Requires-Dist: discord-lumberjack (>=1.0.4,<2.0.0)
Requires-Dist: filelock (>=3.4.2,<4.0.0)
Requires-Dist: requests (>=2.27.0,<3.0.0)
Project-URL: Repository, https://github.com/aidanmelen/bobcat-miner-python
